[
  {
    "id": "GR7vTA_btqTnLtXcEDX8C",
    "companyId": "pVbRRBQtMVw6lUAkj1k43",
    "title": "Backend Developer",
    "description": "We are looking for a Backend Developer familiar with Node.js and Express."
  },
  {
    "id": "yX71WsWqBRAFuMAIDj4W0",
    "companyId": "wvdB54Gqbdp_NZTXK9Tue",
    "title": "Full-Stack Developer",
    "description": "We are looking for a Full-Stack Developer familiar with Node.js, Express, and React."
  },
  {
    "id": "ayZuurzAoci6vx6OQcR3R",
    "title": "BLAH",
    "companyId": "wvdB54Gqbdp_NZTXK9Tue",
    "description": "BLAH - test"
  },
  {
    "id": "Hw4R4F62FQDY5Nj4iu4Y0",
    "title": "Designer",
    "companyId": "wvdB54Gqbdp_NZTXK9Tue",
    "description": "UI UX"
  },
  {
    "id": "4DtTdu3UwPHFUliTytvX3",
    "title": "DevOps Engineer",
    "companyId": "wvdB54Gqbdp_NZTXK9Tue",
    "description": "RESTART SERVER"
  }
]